README
setup.py
bambu_attachments/__init__.py
bambu_attachments/admin.py
bambu_attachments/apps.py
bambu_attachments/forms.py
bambu_attachments/helpers.py
bambu_attachments/models.py
bambu_attachments.egg-info/PKG-INFO
bambu_attachments.egg-info/SOURCES.txt
bambu_attachments.egg-info/dependency_links.txt
bambu_attachments.egg-info/requires.txt
bambu_attachments.egg-info/top_level.txt
bambu_attachments/migrations/0001_initial.py
bambu_attachments/migrations/__init__.py
bambu_attachments/templates/attachments/download.inc.html
bambu_attachments/templates/attachments/image.inc.html
bambu_attachments/templates/attachments/video.inc.html
bambu_attachments/templatetags/__init__.py
bambu_attachments/templatetags/attachments.py