Metadata-Version: 1.1
Name: bambu-attachments
Version: 3.1
Summary: A setup for handling generic model attachments
Home-page: https://github.com/iamsteadman/bambu-attachments
Author: Steadman
Author-email: mark@steadman.io
License: UNKNOWN
Platform: UNKNOWN
Classifier: Development Status :: 4 - Beta
Classifier: Environment :: Web Environment
Classifier: Framework :: Django
